oneNeuron/__init__.py
oneNeuron/perceptron.py
perceptron_pypi_Rukhsar111-0.0.3.dist-info/LICENSE
perceptron_pypi_Rukhsar111-0.0.3.dist-info/METADATA
perceptron_pypi_Rukhsar111-0.0.3.dist-info/WHEEL
perceptron_pypi_Rukhsar111-0.0.3.dist-info/top_level.txt
perceptron_pypi_Rukhsar111-0.0.3.dist-info/RECORD
